sphinxext_altair/__init__.py
sphinxext_altair/altairplot.py
sphinxext_altair/py.typed
sphinxext_altair-0.2.0.dist-info/METADATA
sphinxext_altair-0.2.0.dist-info/WHEEL
sphinxext_altair-0.2.0.dist-info/licenses/LICENSE
sphinxext_altair-0.2.0.dist-info/RECORD
