Metadata-Version: 2.1
Name: sphinxext-altair
Version: 0.2.0
Summary: sphinxext-altair: Sphinx extension for embedding Altair charts
Project-URL: Source, https://github.com/altair-viz/sphinxext-altair
Author: sphinxext-altair Contributors
License-File: LICENSE
Keywords: altair,sphinxext
Classifier: Development Status :: 5 - Production/Stable
Classifier: Environment :: Plugins
Classifier: Framework :: Sphinx :: Extension
Classifier: License :: OSI Approved :: BSD License
Classifier: Natural Language :: English
Classifier: Programming Language :: Python :: 3.7
Classifier: Programming Language :: Python :: 3.8
Classifier: Programming Language :: Python :: 3.9
Classifier: Programming Language :: Python :: 3.10
Classifier: Programming Language :: Python :: 3.11
Classifier: Typing :: Typed
Requires-Python: >=3.7
Requires-Dist: altair>=4.0.0
Requires-Dist: docutils
Requires-Dist: jinja2
Requires-Dist: sphinx
Requires-Dist: typing-extensions>=4.0.1; python_version < '3.8'
Provides-Extra: dev
Requires-Dist: black<24; extra == 'dev'
Requires-Dist: hatch; extra == 'dev'
Requires-Dist: ipython; extra == 'dev'
Requires-Dist: mypy; extra == 'dev'
Requires-Dist: pytest; extra == 'dev'
Requires-Dist: ruff; extra == 'dev'
Requires-Dist: types-docutils; extra == 'dev'
